setup.cfg
setup.py
asyncbattlerite/__init__.py
asyncbattlerite/brclient.py
asyncbattlerite/errors.py
asyncbattlerite/models.py
asyncbattlerite/utils.py
asyncbattlerite.egg-info/PKG-INFO
asyncbattlerite.egg-info/SOURCES.txt
asyncbattlerite.egg-info/dependency_links.txt
asyncbattlerite.egg-info/requires.txt
asyncbattlerite.egg-info/top_level.txt