Metadata-Version: 1.1
Name: asyncbattlerite
Version: 0.5.13
Summary: A non-blocking async wrapper for the madglory Battlerite API
Home-page: https://github.com/xKynn/AsyncBattlerite
Author: xKynn
Author-email: xkynn@github.com
License: UNKNOWN
Download-URL: https://github.com/xKynn/AsyncBattlerite/archive/0.5.13.tar.gz
Keywords: battlerite,asyncbattlerite,async-battlerite,async_battlerite
Platform: UNKNOWN
